{
  "db_name": "SQLite",
  "query": "SELECT c.id AS \"id!: i64\",\n                  c.thread_id AS \"thread_id!: i64\",\n                  c.parent_comment_id AS \"parent_comment_id?: i64\",\n                  c.author_id AS \"author_id!: i64\",\n                  COALESCE(u.display_name, u.username, '?') AS \"author_name!: String\",\n                  c.body,\n                  c.created_at AS \"created_at!: NaiveDateTime\",\n                  c.deleted_at AS \"deleted_at?: NaiveDateTime\"\n           FROM thread_comments c\n           JOIN users u ON u.id = c.author_id\n           WHERE c.thread_id = ?\n           ORDER BY c.created_at, c.id",
  "describe": {
    "columns": [
      {
        "name": "id!: i64",
        "ordinal": 0,
        "type_info": "Integer"
      },
      {
        "name": "thread_id!: i64",
        "ordinal": 1,
        "type_info": "Integer"
      },
      {
        "name": "parent_comment_id?: i64",
        "ordinal": 2,
        "type_info": "Integer"
      },
      {
        "name": "author_id!: i64",
        "ordinal": 3,
        "type_info": "Integer"
      },
      {
        "name": "author_name!: String",
        "ordinal": 4,
        "type_info": "Null"
      },
      {
        "name": "body",
        "ordinal": 5,
        "type_info": "Text"
      },
      {
        "name": "created_at!: NaiveDateTime",
        "ordinal": 6,
        "type_info": "Datetime"
      },
      {
        "name": "deleted_at?: NaiveDateTime",
        "ordinal": 7,
        "type_info": "Datetime"
      }
    ],
    "parameters": {
      "Right": 1
    },
    "nullable": [
      true,
      false,
      true,
      false,
      null,
      false,
      false,
      true
    ]
  },
  "hash": "8527cd5427810301dc71eff2c5fd1e0fd8b305abf4a4bb0575f5541a0ca766fc"
}
